{"de_dust2":[{"bestname":"car smoke","description":"jump throw smoke car","distance":22.647296905517578,"distance_alpha":0.9999999403953552,"distance_width_mp":1.0,"grenade":{"jump":true},"icon_offset":0.0,"in_fov_select_mp":1.0,"in_range":true,"in_range_text":true,"is_visible":true,"name":"car smoke","offscreen_offset":0.0,"on_fov":false,"on_fov_color":0.0,"original_distance":22.647296905517578,"position":[179.6569061279297,-351.58966064453125,0.18082809448242188],"red_color":true,"show_icon":true,"text_offset":0.0,"viewangles":[-17.250877380371094,53.58174133300781],"visible_alpha":1.0,"weapon":"weapon_smokegrenade"},{"bestname":"long smoke","description":"smokes long corner","distance":0.0,"distance_alpha":1.0,"distance_width_mp":1.0,"icon_offset":0.0,"in_fov_select_mp":1.0,"in_range":true,"in_range_text":true,"is_visible":true,"name":"long smoke","offscreen_offset":0.0,"on_fov":false,"on_fov_color":0.6387315988540649,"original_distance":0.0,"position":[656.0494384765625,-188.30960083007813,-1.1672040224075317],"red_color":true,"show_icon":true,"text_offset":0.0,"viewangles":[-44.020484924316406,67.29151153564453],"visible_alpha":1.0,"weapon":"weapon_smokegrenade"},{"bestname":"top mid smoke","description":"smokes top mid","distance":19.86529541015625,"distance_alpha":0.9999999403953552,"distance_width_mp":1.0,"icon_offset":0.0,"in_fov_select_mp":1.0,"in_range":true,"in_range_text":true,"is_visible":true,"name":"top mid smoke","offscreen_offset":0.0,"on_fov":false,"on_fov_color":0.0,"original_distance":19.86529541015625,"position":[-531.2277221679688,-1008.199951171875,129.01522827148438],"red_color":true,"show_icon":true,"text_offset":0.0,"viewangles":[-23.129608154296875,84.53945922851563],"visible_alpha":1.0,"weapon":"weapon_smokegrenade"},{"bestname":"b doors","distance":0.0,"distance_alpha":1.0,"distance_width_mp":1.0,"icon_offset":0.0,"in_fov_select_mp":1.0,"in_range":true,"in_range_text":true,"is_visible":true,"name":"b doors","offscreen_offset":0.0,"on_fov":true,"on_fov_color":1.0,"original_distance":0.0,"position":[-1835.5081787109375,1226.18115234375,32.13402557373047],"red_color":true,"show_icon":true,"text_offset":0.0,"viewangles":[-65.89765167236328,63.32131576538086],"visible_alpha":1.0,"weapon":"weapon_smokegrenade"},{"bestname":"ct smoke","description":"ct smoke from xbox","distance":0.0,"distance_alpha":1.0,"distance_width_mp":1.0,"icon_offset":0.0,"in_fov_select_mp":1.0,"in_range":true,"in_range_text":true,"is_visible":true,"name":"ct smoke","offscreen_offset":0.0,"on_fov":true,"on_fov_color":1.0,"original_distance":0.0,"position":[-275.0009765625,1345.4031982421875,-122.46342468261719],"red_color":true,"show_icon":true,"text_offset":0.0,"viewangles":[-32.36964416503906,132.4087677001953],"visible_alpha":1.0,"weapon":"weapon_smokegrenade"},{"grenade":{"jump":true},"name":"xbox smoke","position":[-502.65997314453125,-661.3406372070313,127.13909912109375],"red_color":true,"viewangles":[-6.172722816467285,85.04122924804688],"weapon":"weapon_smokegrenade"}]}